byted_overpass_tns_algo_eng_auto_iteration/__init__.py
byted_overpass_tns_algo_eng_auto_iteration-0.0.1.dist-info/METADATA
byted_overpass_tns_algo_eng_auto_iteration-0.0.1.dist-info/WHEEL
byted_overpass_tns_algo_eng_auto_iteration-0.0.1.dist-info/top_level.txt
byted_overpass_tns_algo_eng_auto_iteration-0.0.1.dist-info/RECORD
